gaps/__init__.py
gaps/assign.py
gaps-0.1.1.dist-info/LICENSE.md
gaps-0.1.1.dist-info/WHEEL
gaps-0.1.1.dist-info/METADATA
gaps-0.1.1.dist-info/RECORD
